{
  "modo_operacao": "NORMAL",

  "tempo_espera": 5,

  "gerenciamento": {

    "max_ordens": 1,

    "stop_individual": 30,

    "tp_multiplicador": 2,

    "trailing": {

      "ativo": true,

      "ativar_em": 100,

      "reter_percentual": 75
    }
  },

  "ativos": [

    {
      "symbol": "XAUUSD",

      "enabled": true,

      "lote": 0.01,

      "spread_max": 130,

      "stop": 600,

      "tp": 1000,

      "cooldown": 600
    },

    {
      "symbol": "BTCUSD",

      "enabled": true,

      "lote": 0.01,

      "spread_max": 2000,

      "stop": 3500,

      "tp": 7000,

      "cooldown": 1800
    },

    {
      "symbol": "EURUSD",

      "enabled": true,

      "lote": 0.05,

      "spread_max": 25,

      "stop": 150,

      "tp": 300,

      "cooldown": 240
    },

    {
      "symbol": "USDJPY",

      "enabled": true,

      "lote": 0.05,

      "spread_max": 35,

      "stop": 180,

      "tp": 360,

      "cooldown": 300
    }
  ]
}
