{
  "cliente": "ALEX",
  "timestamp": "2026-06-21 13:29:18",
  "status": "ONLINE",
  "github": "ERRO",
  "modo": "MODERADO",
  "timeframe": "M5",
  "posicoes": 1,
  "max_positions": 1,
  "saldo": 941.21,
  "equity": 955.34,
  "margem_livre": 954.18,
  "lucro_aberto": 14.13,
  "drawdown_percent": 0.0,
  "controle_remoto": {
    "bloquear_operacao": false,
    "acao": "SAFE",
    "mensagem": "modo seguro ativado"
  },
  "risk_control": {
    "ativo": true,
    "daily_loss_limit_usd": 10.0,
    "max_drawdown_percent": 3.0,
    "emergency_close": false
  },
  "ativos": {
    "BTCUSD": {
      "perfil": "AGRESSIVO",
      "status": "SEM POSICAO",
      "posicoes": 0,
      "lado": "NONE",
      "lucro": 0.0,
      "score_ia": 0,
      "regime": "AGUARDANDO",
      "confianca": 0,
      "acao_ia": "AGUARDANDO"
    },
    "XAUUSD": {
      "perfil": "AGRESSIVO",
      "status": "SEM POSICAO",
      "posicoes": 0,
      "lado": "NONE",
      "lucro": 0.0,
      "score_ia": 25,
      "regime": "RANGING",
      "confianca": 25,
      "acao_ia": "IGNORAR"
    },
    "EURUSD": {
      "perfil": "CONSERVADOR",
      "status": "SEM POSICAO",
      "posicoes": 0,
      "lado": "NONE",
      "lucro": 0.0,
      "score_ia": 65,
      "regime": "RANGING",
      "confianca": 65,
      "acao_ia": "BLOQUEAR"
    },
    "USDJPY": {
      "perfil": "CONSERVADOR",
      "status": "SEM POSICAO",
      "posicoes": 0,
      "lado": "NONE",
      "lucro": 0.0,
      "score_ia": 25,
      "regime": "RANGING",
      "confianca": 25,
      "acao_ia": "IGNORAR"
    }
  }
}